configs/het_net_placement.yaml
pytwinnet/__about__.py
pytwinnet/__init__.py
pytwinnet/accelerate/__init__.py
pytwinnet/accelerate/association.py
pytwinnet/accelerate/numba_kernels.py
pytwinnet/accelerate/vectorized.py
pytwinnet/cli/__init__.py
pytwinnet/cli/__main__.py
pytwinnet/cli/main.py
pytwinnet/core/__init__.py
pytwinnet/core/digital_twin.py
pytwinnet/core/network.py
pytwinnet/core/node.py
pytwinnet/core/transceiver.py
pytwinnet/core/utils.py
pytwinnet/dashboard/__init__.py
pytwinnet/dashboard/streamlit_app.py
pytwinnet/handover/__init__.py
pytwinnet/handover/rules.py
pytwinnet/ingestion/__init__.py
pytwinnet/ingestion/base.py
pytwinnet/ingestion/csv_adapter.py
pytwinnet/ingestion/mock.py
pytwinnet/ingestion/realtime.py
pytwinnet/mimo/__init__.py
pytwinnet/mimo/channel.py
pytwinnet/mobility/__init__.py
pytwinnet/mobility/constant_velocity.py
pytwinnet/mobility/random_waypoint.py
pytwinnet/optimization/__init__.py
pytwinnet/optimization/bayesopt.py
pytwinnet/optimization/ga.py
pytwinnet/optimization/grid_search.py
pytwinnet/optimization/objective.py
pytwinnet/optimization/objective_ext.py
pytwinnet/optimization/optimizer.py
pytwinnet/optimization/pareto.py
pytwinnet/optimization/placement.py
pytwinnet/optimization/placement_parallel.py
pytwinnet/optimization/random_search.py
pytwinnet/optimization/simple_greedy.py
pytwinnet/physics/__init__.py
pytwinnet/physics/batch.py
pytwinnet/physics/environment.py
pytwinnet/physics/fading.py
pytwinnet/physics/link_budget.py
pytwinnet/physics/propagation.py
pytwinnet/physics/ris.py
pytwinnet/physics/ris_beam.py
pytwinnet/physics/signal.py
pytwinnet/ris/__init__.py
pytwinnet/ris/beamforming.py
pytwinnet/rl/__init__.py
pytwinnet/rl/power_env.py
pytwinnet/scheduling/__init__.py
pytwinnet/scheduling/association.py
pytwinnet/scheduling/max_sinr.py
pytwinnet/scheduling/pf_scheduler.py
pytwinnet/scheduling/rr.py
pytwinnet/simulation/__init__.py
pytwinnet/simulation/events.py
pytwinnet/simulation/scenario.py
pytwinnet-0.1.3.dist-info/METADATA
pytwinnet-0.1.3.dist-info/WHEEL
pytwinnet-0.1.3.dist-info/entry_points.txt
pytwinnet-0.1.3.dist-info/top_level.txt
pytwinnet-0.1.3.dist-info/RECORD
